adafruit_jd79661.py
adafruit_circuitpython_jd79661-1.0.2.dist-info/licenses/LICENSE
adafruit_circuitpython_jd79661-1.0.2.dist-info/METADATA
adafruit_circuitpython_jd79661-1.0.2.dist-info/WHEEL
adafruit_circuitpython_jd79661-1.0.2.dist-info/top_level.txt
adafruit_circuitpython_jd79661-1.0.2.dist-info/RECORD
